{"ccn": "010079", "name": "ATHENS LIMESTONE HOSPITAL", "location": {"city": "ATHENS", "state": "AL"}, "updated": "2026-04-07", "prices": [{"code": "71045", "desc": "Chest X-Ray 1 View", "price": 159.0}, {"code": "80053", "desc": "Comprehensive Metabolic Panel", "price": 251.0}, {"code": "80053", "desc": "Comprehensive Metabolic Panel", "price": 403.0}, {"code": "12001", "desc": "Simple Repair of Superficial Wounds (Stitches)", "price": 556.0}, {"code": "99283", "desc": "ER Visit, Level 3", "price": 888.0}, {"code": "74177", "desc": "CT Scan Abdomen and Pelvis with Dye", "price": 1265.0}, {"code": "99283", "desc": "ER Visit, Level 3", "price": 1387.0}, {"code": "45378", "desc": "Colonoscopy Diagnostic", "price": 2822.0}, {"code": "27447", "desc": "Knee Replacement", "price": 26184.0}, {"code": "27130", "desc": "Hip Replacement", "price": 32605.0}, {"code": "27130", "desc": "Hip Replacement", "price": 42095.0}, {"code": "27447", "desc": "Knee Replacement", "price": 42288.0}, {"code": "27447", "desc": "Knee Replacement", "price": 43132.0}]}