{"ccn": "011308", "name": "CRENSHAW COMMUNITY HOSPITAL", "location": {"city": "LUVERNE", "state": "AL"}, "updated": "2026-04-07", "prices": [{"code": "80053", "desc": "Comprehensive Metabolic Panel", "price": 354.0}, {"code": "99283", "desc": "ER Visit, Level 3", "price": 1047.0}, {"code": "74177", "desc": "CT Scan Abdomen and Pelvis with Dye", "price": 1084.0}, {"code": "99283", "desc": "ER Visit, Level 3", "price": 1225.0}, {"code": "74177", "desc": "CT Scan Abdomen and Pelvis with Dye", "price": 1379.0}, {"code": "45378", "desc": "Colonoscopy Diagnostic", "price": 1567.0}, {"code": "74177", "desc": "CT Scan Abdomen and Pelvis with Dye", "price": 1673.0}, {"code": "99285", "desc": "ER Visit, Level 5 (Complex/Heart Attack)", "price": 1895.0}, {"code": "99285", "desc": "ER Visit, Level 5 (Complex/Heart Attack)", "price": 2785.0}, {"code": "45378", "desc": "Colonoscopy Diagnostic", "price": 2886.0}, {"code": "59400", "desc": "Obstetrical Care (Labor and Delivery)", "price": 13383.0}, {"code": "27130", "desc": "Hip Replacement", "price": 26567.0}, {"code": "27130", "desc": "Hip Replacement", "price": 45277.0}]}