{"ccn": "050696", "name": "KECK HOSPITAL OF USC", "location": {"city": "LOS ANGELES", "state": "CA"}, "updated": "2026-04-07", "prices": [{"code": "80053", "desc": "Comprehensive Metabolic Panel", "price": 247.0}, {"code": "80053", "desc": "Comprehensive Metabolic Panel", "price": 392.0}, {"code": "99283", "desc": "ER Visit, Level 3", "price": 885.0}, {"code": "70551", "desc": "MRI Brain without Dye", "price": 993.0}, {"code": "99283", "desc": "ER Visit, Level 3", "price": 1013.0}, {"code": "45378", "desc": "Colonoscopy Diagnostic", "price": 1332.0}, {"code": "45378", "desc": "Colonoscopy Diagnostic", "price": 1757.0}, {"code": "70551", "desc": "MRI Brain without Dye", "price": 2072.0}, {"code": "99285", "desc": "ER Visit, Level 5 (Complex/Heart Attack)", "price": 2898.0}, {"code": "74177", "desc": "CT Scan Abdomen and Pelvis with Dye", "price": 2994.0}, {"code": "59400", "desc": "Obstetrical Care (Labor and Delivery)", "price": 8905.0}, {"code": "27130", "desc": "Hip Replacement", "price": 36324.0}, {"code": "27130", "desc": "Hip Replacement", "price": 40293.0}, {"code": "27447", "desc": "Knee Replacement", "price": 49102.0}, {"code": "27447", "desc": "Knee Replacement", "price": 49702.0}]}