{"ccn": "053304", "name": "CHILDREN'S HOSPITAL OF ORANGE COUNTY", "location": {"city": "ORANGE", "state": "CA"}, "updated": "2026-04-07", "prices": [{"code": "71045", "desc": "Chest X-Ray 1 View", "price": 72.0}, {"code": "71045", "desc": "Chest X-Ray 1 View", "price": 137.0}, {"code": "12001", "desc": "Simple Repair of Superficial Wounds (Stitches)", "price": 173.0}, {"code": "70551", "desc": "MRI Brain without Dye", "price": 770.0}, {"code": "99283", "desc": "ER Visit, Level 3", "price": 1105.0}, {"code": "99283", "desc": "ER Visit, Level 3", "price": 1274.0}, {"code": "99285", "desc": "ER Visit, Level 5 (Complex/Heart Attack)", "price": 1707.0}, {"code": "70551", "desc": "MRI Brain without Dye", "price": 1905.0}, {"code": "59400", "desc": "Obstetrical Care (Labor and Delivery)", "price": 9055.0}, {"code": "59400", "desc": "Obstetrical Care (Labor and Delivery)", "price": 11634.0}, {"code": "59400", "desc": "Obstetrical Care (Labor and Delivery)", "price": 13685.0}, {"code": "27447", "desc": "Knee Replacement", "price": 31424.0}]}