{"ccn": "061305", "name": "MELISSA MEMORIAL HOSPITAL", "location": {"city": "HOLYOKE", "state": "CO"}, "updated": "2026-04-07", "prices": [{"code": "71045", "desc": "Chest X-Ray 1 View", "price": 174.0}, {"code": "12001", "desc": "Simple Repair of Superficial Wounds (Stitches)", "price": 177.0}, {"code": "70551", "desc": "MRI Brain without Dye", "price": 1081.0}, {"code": "45378", "desc": "Colonoscopy Diagnostic", "price": 1541.0}, {"code": "99285", "desc": "ER Visit, Level 5 (Complex/Heart Attack)", "price": 1844.0}, {"code": "45378", "desc": "Colonoscopy Diagnostic", "price": 1972.0}, {"code": "70551", "desc": "MRI Brain without Dye", "price": 2128.0}, {"code": "45378", "desc": "Colonoscopy Diagnostic", "price": 2228.0}, {"code": "74177", "desc": "CT Scan Abdomen and Pelvis with Dye", "price": 2348.0}, {"code": "59400", "desc": "Obstetrical Care (Labor and Delivery)", "price": 17625.0}, {"code": "27130", "desc": "Hip Replacement", "price": 33300.0}]}