{"ccn": "110041", "name": "NORTHEAST GEORGIA MEDICAL CENTER HABERSHAM", "location": {"city": "DEMOREST", "state": "GA"}, "updated": "2026-04-07", "prices": [{"code": "71045", "desc": "Chest X-Ray 1 View", "price": 72.0}, {"code": "80053", "desc": "Comprehensive Metabolic Panel", "price": 405.0}, {"code": "12001", "desc": "Simple Repair of Superficial Wounds (Stitches)", "price": 468.0}, {"code": "70551", "desc": "MRI Brain without Dye", "price": 718.0}, {"code": "70551", "desc": "MRI Brain without Dye", "price": 1171.0}, {"code": "74177", "desc": "CT Scan Abdomen and Pelvis with Dye", "price": 2062.0}, {"code": "99285", "desc": "ER Visit, Level 5 (Complex/Heart Attack)", "price": 2648.0}, {"code": "99285", "desc": "ER Visit, Level 5 (Complex/Heart Attack)", "price": 3763.0}, {"code": "45378", "desc": "Colonoscopy Diagnostic", "price": 4125.0}, {"code": "27130", "desc": "Hip Replacement", "price": 38229.0}, {"code": "27447", "desc": "Knee Replacement", "price": 39680.0}, {"code": "27447", "desc": "Knee Replacement", "price": 54918.0}]}