{"ccn": "14008F", "name": "MARION IL VA MEDICAL CENTER", "location": {"city": "MARION", "state": "IL"}, "updated": "2026-04-07", "prices": [{"code": "71045", "desc": "Chest X-Ray 1 View", "price": 117.0}, {"code": "71045", "desc": "Chest X-Ray 1 View", "price": 139.0}, {"code": "12001", "desc": "Simple Repair of Superficial Wounds (Stitches)", "price": 584.0}, {"code": "99283", "desc": "ER Visit, Level 3", "price": 1236.0}, {"code": "74177", "desc": "CT Scan Abdomen and Pelvis with Dye", "price": 1278.0}, {"code": "99285", "desc": "ER Visit, Level 5 (Complex/Heart Attack)", "price": 3215.0}, {"code": "27130", "desc": "Hip Replacement", "price": 23386.0}, {"code": "27130", "desc": "Hip Replacement", "price": 26598.0}, {"code": "27130", "desc": "Hip Replacement", "price": 44552.0}, {"code": "27130", "desc": "Hip Replacement", "price": 47001.0}]}