{"ccn": "151333", "name": "PUTNAM COUNTY HOSPITAL", "location": {"city": "GREENCASTLE", "state": "IN"}, "updated": "2026-04-07", "prices": [{"code": "80053", "desc": "Comprehensive Metabolic Panel", "price": 217.0}, {"code": "80053", "desc": "Comprehensive Metabolic Panel", "price": 372.0}, {"code": "99283", "desc": "ER Visit, Level 3", "price": 1112.0}, {"code": "45378", "desc": "Colonoscopy Diagnostic", "price": 2532.0}, {"code": "74177", "desc": "CT Scan Abdomen and Pelvis with Dye", "price": 2692.0}, {"code": "27447", "desc": "Knee Replacement", "price": 36916.0}, {"code": "27447", "desc": "Knee Replacement", "price": 46491.0}]}