{"ccn": "171349", "name": "CLOUD COUNTY HEALTH CENTER", "location": {"city": "CONCORDIA", "state": "KS"}, "updated": "2026-04-07", "prices": [{"code": "74177", "desc": "CT Scan Abdomen and Pelvis with Dye", "price": 1561.0}, {"code": "70551", "desc": "MRI Brain without Dye", "price": 2064.0}, {"code": "45378", "desc": "Colonoscopy Diagnostic", "price": 2198.0}, {"code": "74177", "desc": "CT Scan Abdomen and Pelvis with Dye", "price": 3398.0}, {"code": "59400", "desc": "Obstetrical Care (Labor and Delivery)", "price": 16839.0}, {"code": "27447", "desc": "Knee Replacement", "price": 52507.0}]}