{"ccn": "180020", "name": "MIDDLESBORO ARH HOSPITAL", "location": {"city": "MIDDLESBORO", "state": "KY"}, "updated": "2026-04-07", "prices": [{"code": "71045", "desc": "Chest X-Ray 1 View", "price": 98.0}, {"code": "80053", "desc": "Comprehensive Metabolic Panel", "price": 331.0}, {"code": "12001", "desc": "Simple Repair of Superficial Wounds (Stitches)", "price": 381.0}, {"code": "99283", "desc": "ER Visit, Level 3", "price": 835.0}, {"code": "70551", "desc": "MRI Brain without Dye", "price": 1073.0}, {"code": "99283", "desc": "ER Visit, Level 3", "price": 1276.0}, {"code": "70551", "desc": "MRI Brain without Dye", "price": 2101.0}, {"code": "45378", "desc": "Colonoscopy Diagnostic", "price": 2229.0}, {"code": "27447", "desc": "Knee Replacement", "price": 28553.0}]}