{"ccn": "190099", "name": "AVOYELLES HOSPITAL", "location": {"city": "MARKSVILLE", "state": "LA"}, "updated": "2026-04-07", "prices": [{"code": "80053", "desc": "Comprehensive Metabolic Panel", "price": 404.0}, {"code": "12001", "desc": "Simple Repair of Superficial Wounds (Stitches)", "price": 450.0}, {"code": "12001", "desc": "Simple Repair of Superficial Wounds (Stitches)", "price": 582.0}, {"code": "70551", "desc": "MRI Brain without Dye", "price": 645.0}, {"code": "74177", "desc": "CT Scan Abdomen and Pelvis with Dye", "price": 2020.0}, {"code": "99285", "desc": "ER Visit, Level 5 (Complex/Heart Attack)", "price": 2202.0}, {"code": "74177", "desc": "CT Scan Abdomen and Pelvis with Dye", "price": 2515.0}, {"code": "74177", "desc": "CT Scan Abdomen and Pelvis with Dye", "price": 3100.0}, {"code": "59400", "desc": "Obstetrical Care (Labor and Delivery)", "price": 17665.0}]}