{"ccn": "194086", "name": "OCEANS BEHAVIORAL HOSPITAL OF BATON ROUGE", "location": {"city": "BATON ROUGE", "state": "LA"}, "updated": "2026-04-07", "prices": [{"code": "71045", "desc": "Chest X-Ray 1 View", "price": 80.0}, {"code": "71045", "desc": "Chest X-Ray 1 View", "price": 176.0}, {"code": "80053", "desc": "Comprehensive Metabolic Panel", "price": 286.0}, {"code": "12001", "desc": "Simple Repair of Superficial Wounds (Stitches)", "price": 480.0}, {"code": "45378", "desc": "Colonoscopy Diagnostic", "price": 2172.0}, {"code": "45378", "desc": "Colonoscopy Diagnostic", "price": 2237.0}, {"code": "45378", "desc": "Colonoscopy Diagnostic", "price": 3137.0}, {"code": "59400", "desc": "Obstetrical Care (Labor and Delivery)", "price": 8890.0}, {"code": "59400", "desc": "Obstetrical Care (Labor and Delivery)", "price": 12543.0}, {"code": "27447", "desc": "Knee Replacement", "price": 47494.0}]}