{"ccn": "210018", "name": "MEDSTAR MONTGOMERY MEDICAL CENTER", "location": {"city": "OLNEY", "state": "MD"}, "updated": "2026-04-07", "prices": [{"code": "71045", "desc": "Chest X-Ray 1 View", "price": 121.0}, {"code": "71045", "desc": "Chest X-Ray 1 View", "price": 179.0}, {"code": "80053", "desc": "Comprehensive Metabolic Panel", "price": 286.0}, {"code": "12001", "desc": "Simple Repair of Superficial Wounds (Stitches)", "price": 358.0}, {"code": "12001", "desc": "Simple Repair of Superficial Wounds (Stitches)", "price": 488.0}, {"code": "99283", "desc": "ER Visit, Level 3", "price": 1274.0}, {"code": "74177", "desc": "CT Scan Abdomen and Pelvis with Dye", "price": 1723.0}, {"code": "70551", "desc": "MRI Brain without Dye", "price": 2010.0}, {"code": "27130", "desc": "Hip Replacement", "price": 25246.0}, {"code": "27130", "desc": "Hip Replacement", "price": 25861.0}, {"code": "27447", "desc": "Knee Replacement", "price": 36218.0}, {"code": "27447", "desc": "Knee Replacement", "price": 36336.0}]}