{"ccn": "310047", "name": "SHORE MEDICAL CENTER", "location": {"city": "SOMERS POINT", "state": "NJ"}, "updated": "2026-04-07", "prices": [{"code": "71045", "desc": "Chest X-Ray 1 View", "price": 89.0}, {"code": "12001", "desc": "Simple Repair of Superficial Wounds (Stitches)", "price": 510.0}, {"code": "99283", "desc": "ER Visit, Level 3", "price": 926.0}, {"code": "70551", "desc": "MRI Brain without Dye", "price": 1937.0}, {"code": "99285", "desc": "ER Visit, Level 5 (Complex/Heart Attack)", "price": 2743.0}, {"code": "99285", "desc": "ER Visit, Level 5 (Complex/Heart Attack)", "price": 2774.0}, {"code": "45378", "desc": "Colonoscopy Diagnostic", "price": 3516.0}, {"code": "59400", "desc": "Obstetrical Care (Labor and Delivery)", "price": 16218.0}, {"code": "27447", "desc": "Knee Replacement", "price": 27765.0}, {"code": "27130", "desc": "Hip Replacement", "price": 39363.0}, {"code": "27447", "desc": "Knee Replacement", "price": 48279.0}]}