{"ccn": "310005", "name": "HUNTERDON MEDICAL CENTER", "location": {"city": "FLEMINGTON", "state": "NJ"}, "updated": "2026-04-07", "prices": [{"code": "71045", "desc": "Chest X-Ray 1 View", "price": 75.0}, {"code": "80053", "desc": "Comprehensive Metabolic Panel", "price": 125.0}, {"code": "71045", "desc": "Chest X-Ray 1 View", "price": 176.0}, {"code": "80053", "desc": "Comprehensive Metabolic Panel", "price": 317.0}, {"code": "80053", "desc": "Comprehensive Metabolic Panel", "price": 419.0}, {"code": "12001", "desc": "Simple Repair of Superficial Wounds (Stitches)", "price": 562.0}, {"code": "99283", "desc": "ER Visit, Level 3", "price": 816.0}, {"code": "99283", "desc": "ER Visit, Level 3", "price": 914.0}, {"code": "74177", "desc": "CT Scan Abdomen and Pelvis with Dye", "price": 923.0}, {"code": "74177", "desc": "CT Scan Abdomen and Pelvis with Dye", "price": 1144.0}, {"code": "70551", "desc": "MRI Brain without Dye", "price": 1481.0}, {"code": "74177", "desc": "CT Scan Abdomen and Pelvis with Dye", "price": 1981.0}, {"code": "74177", "desc": "CT Scan Abdomen and Pelvis with Dye", "price": 3021.0}, {"code": "45378", "desc": "Colonoscopy Diagnostic", "price": 4122.0}, {"code": "99285", "desc": "ER Visit, Level 5 (Complex/Heart Attack)", "price": 4160.0}, {"code": "27447", "desc": "Knee Replacement", "price": 37320.0}, {"code": "27130", "desc": "Hip Replacement", "price": 40782.0}, {"code": "27447", "desc": "Knee Replacement", "price": 51112.0}]}