{"ccn": "310027", "name": "TRINITAS REGIONAL MEDICAL CENTER", "location": {"city": "ELIZABETH", "state": "NJ"}, "updated": "2026-04-07", "prices": [{"code": "80053", "desc": "Comprehensive Metabolic Panel", "price": 397.0}, {"code": "70551", "desc": "MRI Brain without Dye", "price": 1664.0}, {"code": "74177", "desc": "CT Scan Abdomen and Pelvis with Dye", "price": 2233.0}, {"code": "74177", "desc": "CT Scan Abdomen and Pelvis with Dye", "price": 2628.0}, {"code": "74177", "desc": "CT Scan Abdomen and Pelvis with Dye", "price": 2654.0}, {"code": "45378", "desc": "Colonoscopy Diagnostic", "price": 3034.0}, {"code": "27447", "desc": "Knee Replacement", "price": 37405.0}]}