{"ccn": "33017F", "name": "VA NEW YORK HARBOR HEALTHCARE SYSTEM - NY DIV.", "location": {"city": "NEW YORK", "state": "NY"}, "updated": "2026-04-07", "prices": [{"code": "71045", "desc": "Chest X-Ray 1 View", "price": 174.0}, {"code": "80053", "desc": "Comprehensive Metabolic Panel", "price": 238.0}, {"code": "80053", "desc": "Comprehensive Metabolic Panel", "price": 359.0}, {"code": "12001", "desc": "Simple Repair of Superficial Wounds (Stitches)", "price": 455.0}, {"code": "99283", "desc": "ER Visit, Level 3", "price": 1071.0}, {"code": "70551", "desc": "MRI Brain without Dye", "price": 2191.0}, {"code": "99285", "desc": "ER Visit, Level 5 (Complex/Heart Attack)", "price": 2382.0}, {"code": "99285", "desc": "ER Visit, Level 5 (Complex/Heart Attack)", "price": 2921.0}, {"code": "27447", "desc": "Knee Replacement", "price": 42899.0}]}