{"ccn": "330265", "name": "CLIFTON SPRINGS HOSPITAL AND CLINIC", "location": {"city": "CLIFTON SPRINGS", "state": "NY"}, "updated": "2026-04-07", "prices": [{"code": "71045", "desc": "Chest X-Ray 1 View", "price": 84.0}, {"code": "12001", "desc": "Simple Repair of Superficial Wounds (Stitches)", "price": 483.0}, {"code": "74177", "desc": "CT Scan Abdomen and Pelvis with Dye", "price": 1250.0}, {"code": "74177", "desc": "CT Scan Abdomen and Pelvis with Dye", "price": 1314.0}, {"code": "70551", "desc": "MRI Brain without Dye", "price": 1386.0}, {"code": "74177", "desc": "CT Scan Abdomen and Pelvis with Dye", "price": 1562.0}, {"code": "70551", "desc": "MRI Brain without Dye", "price": 1826.0}, {"code": "74177", "desc": "CT Scan Abdomen and Pelvis with Dye", "price": 2208.0}, {"code": "99285", "desc": "ER Visit, Level 5 (Complex/Heart Attack)", "price": 2488.0}, {"code": "74177", "desc": "CT Scan Abdomen and Pelvis with Dye", "price": 2564.0}, {"code": "74177", "desc": "CT Scan Abdomen and Pelvis with Dye", "price": 3281.0}, {"code": "59400", "desc": "Obstetrical Care (Labor and Delivery)", "price": 14835.0}, {"code": "27130", "desc": "Hip Replacement", "price": 24614.0}, {"code": "27130", "desc": "Hip Replacement", "price": 28915.0}, {"code": "27130", "desc": "Hip Replacement", "price": 39532.0}]}