{"ccn": "360016", "name": "THE JEWISH HOSPITAL-MERCY HEALTH", "location": {"city": "CINCINNATI", "state": "OH"}, "updated": "2026-04-07", "prices": [{"code": "71045", "desc": "Chest X-Ray 1 View", "price": 133.0}, {"code": "99283", "desc": "ER Visit, Level 3", "price": 754.0}, {"code": "99283", "desc": "ER Visit, Level 3", "price": 866.0}, {"code": "99283", "desc": "ER Visit, Level 3", "price": 1027.0}, {"code": "70551", "desc": "MRI Brain without Dye", "price": 1343.0}, {"code": "99285", "desc": "ER Visit, Level 5 (Complex/Heart Attack)", "price": 3222.0}, {"code": "99285", "desc": "ER Visit, Level 5 (Complex/Heart Attack)", "price": 3532.0}, {"code": "59400", "desc": "Obstetrical Care (Labor and Delivery)", "price": 14712.0}, {"code": "27447", "desc": "Knee Replacement", "price": 35668.0}, {"code": "27130", "desc": "Hip Replacement", "price": 36408.0}]}