{"ccn": "371304", "name": "MERCY HOSPITAL TISHOMINGO INC", "location": {"city": "TISHOMINGO", "state": "OK"}, "updated": "2026-04-07", "prices": [{"code": "80053", "desc": "Comprehensive Metabolic Panel", "price": 177.0}, {"code": "70551", "desc": "MRI Brain without Dye", "price": 790.0}, {"code": "70551", "desc": "MRI Brain without Dye", "price": 1352.0}, {"code": "74177", "desc": "CT Scan Abdomen and Pelvis with Dye", "price": 1591.0}, {"code": "45378", "desc": "Colonoscopy Diagnostic", "price": 2118.0}, {"code": "74177", "desc": "CT Scan Abdomen and Pelvis with Dye", "price": 2786.0}, {"code": "59400", "desc": "Obstetrical Care (Labor and Delivery)", "price": 9120.0}, {"code": "27130", "desc": "Hip Replacement", "price": 28374.0}, {"code": "27447", "desc": "Knee Replacement", "price": 50535.0}]}