{"ccn": "380022", "name": "SAMARITAN ALBANY GENERAL HOSPITAL", "location": {"city": "ALBANY", "state": "OR"}, "updated": "2026-04-07", "prices": [{"code": "71045", "desc": "Chest X-Ray 1 View", "price": 174.0}, {"code": "12001", "desc": "Simple Repair of Superficial Wounds (Stitches)", "price": 311.0}, {"code": "12001", "desc": "Simple Repair of Superficial Wounds (Stitches)", "price": 375.0}, {"code": "99283", "desc": "ER Visit, Level 3", "price": 504.0}, {"code": "70551", "desc": "MRI Brain without Dye", "price": 826.0}, {"code": "99283", "desc": "ER Visit, Level 3", "price": 1450.0}, {"code": "70551", "desc": "MRI Brain without Dye", "price": 2044.0}, {"code": "45378", "desc": "Colonoscopy Diagnostic", "price": 2203.0}, {"code": "99285", "desc": "ER Visit, Level 5 (Complex/Heart Attack)", "price": 2395.0}, {"code": "74177", "desc": "CT Scan Abdomen and Pelvis with Dye", "price": 3177.0}]}