{"ccn": "380090", "name": "BAY AREA HOSPITAL", "location": {"city": "COOS BAY", "state": "OR"}, "updated": "2026-04-07", "prices": [{"code": "71045", "desc": "Chest X-Ray 1 View", "price": 132.0}, {"code": "71045", "desc": "Chest X-Ray 1 View", "price": 133.0}, {"code": "71045", "desc": "Chest X-Ray 1 View", "price": 165.0}, {"code": "12001", "desc": "Simple Repair of Superficial Wounds (Stitches)", "price": 236.0}, {"code": "12001", "desc": "Simple Repair of Superficial Wounds (Stitches)", "price": 584.0}, {"code": "70551", "desc": "MRI Brain without Dye", "price": 967.0}, {"code": "99283", "desc": "ER Visit, Level 3", "price": 1077.0}, {"code": "99283", "desc": "ER Visit, Level 3", "price": 1165.0}, {"code": "99283", "desc": "ER Visit, Level 3", "price": 1219.0}, {"code": "99285", "desc": "ER Visit, Level 5 (Complex/Heart Attack)", "price": 3171.0}, {"code": "45378", "desc": "Colonoscopy Diagnostic", "price": 3730.0}, {"code": "99285", "desc": "ER Visit, Level 5 (Complex/Heart Attack)", "price": 3784.0}, {"code": "59400", "desc": "Obstetrical Care (Labor and Delivery)", "price": 14927.0}, {"code": "27130", "desc": "Hip Replacement", "price": 25457.0}, {"code": "27130", "desc": "Hip Replacement", "price": 27912.0}, {"code": "27130", "desc": "Hip Replacement", "price": 29724.0}, {"code": "27447", "desc": "Knee Replacement", "price": 36997.0}, {"code": "27130", "desc": "Hip Replacement", "price": 40946.0}]}