{"ccn": "400012", "name": "HOSPITAL ONCOLOGICO DR ISAAC GONZALEZ MARTINEZ", "location": {"city": "SAN JUAN", "state": "PR"}, "updated": "2026-04-07", "prices": [{"code": "80053", "desc": "Comprehensive Metabolic Panel", "price": 147.0}, {"code": "12001", "desc": "Simple Repair of Superficial Wounds (Stitches)", "price": 203.0}, {"code": "80053", "desc": "Comprehensive Metabolic Panel", "price": 406.0}, {"code": "99283", "desc": "ER Visit, Level 3", "price": 720.0}, {"code": "70551", "desc": "MRI Brain without Dye", "price": 1194.0}, {"code": "45378", "desc": "Colonoscopy Diagnostic", "price": 1204.0}, {"code": "74177", "desc": "CT Scan Abdomen and Pelvis with Dye", "price": 1556.0}, {"code": "99285", "desc": "ER Visit, Level 5 (Complex/Heart Attack)", "price": 1875.0}, {"code": "74177", "desc": "CT Scan Abdomen and Pelvis with Dye", "price": 2053.0}, {"code": "45378", "desc": "Colonoscopy Diagnostic", "price": 2175.0}, {"code": "74177", "desc": "CT Scan Abdomen and Pelvis with Dye", "price": 2410.0}, {"code": "99285", "desc": "ER Visit, Level 5 (Complex/Heart Attack)", "price": 2517.0}, {"code": "74177", "desc": "CT Scan Abdomen and Pelvis with Dye", "price": 2605.0}, {"code": "45378", "desc": "Colonoscopy Diagnostic", "price": 3043.0}, {"code": "27130", "desc": "Hip Replacement", "price": 31169.0}, {"code": "27130", "desc": "Hip Replacement", "price": 31919.0}]}