{"ccn": "450639", "name": "TEXAS HEALTH HARRIS METHODIST HURST-EULESS-BEDFORD", "location": {"city": "BEDFORD", "state": "TX"}, "updated": "2026-04-07", "prices": [{"code": "12001", "desc": "Simple Repair of Superficial Wounds (Stitches)", "price": 152.0}, {"code": "80053", "desc": "Comprehensive Metabolic Panel", "price": 331.0}, {"code": "12001", "desc": "Simple Repair of Superficial Wounds (Stitches)", "price": 576.0}, {"code": "12001", "desc": "Simple Repair of Superficial Wounds (Stitches)", "price": 578.0}, {"code": "99285", "desc": "ER Visit, Level 5 (Complex/Heart Attack)", "price": 2072.0}, {"code": "45378", "desc": "Colonoscopy Diagnostic", "price": 2635.0}]}