{"ccn": "451395", "name": "HILL REGIONAL HOSPITAL", "location": {"city": "HILLSBORO", "state": "TX"}, "updated": "2026-04-07", "prices": [{"code": "71045", "desc": "Chest X-Ray 1 View", "price": 56.0}, {"code": "80053", "desc": "Comprehensive Metabolic Panel", "price": 120.0}, {"code": "71045", "desc": "Chest X-Ray 1 View", "price": 141.0}, {"code": "12001", "desc": "Simple Repair of Superficial Wounds (Stitches)", "price": 286.0}, {"code": "45378", "desc": "Colonoscopy Diagnostic", "price": 2014.0}, {"code": "74177", "desc": "CT Scan Abdomen and Pelvis with Dye", "price": 2864.0}, {"code": "99285", "desc": "ER Visit, Level 5 (Complex/Heart Attack)", "price": 3292.0}, {"code": "59400", "desc": "Obstetrical Care (Labor and Delivery)", "price": 15312.0}, {"code": "27130", "desc": "Hip Replacement", "price": 36271.0}]}