{"ccn": "454139", "name": "SUN BEHAVIORAL HOUSTON", "location": {"city": "HOUSTON", "state": "TX"}, "updated": "2026-04-07", "prices": [{"code": "71045", "desc": "Chest X-Ray 1 View", "price": 52.0}, {"code": "71045", "desc": "Chest X-Ray 1 View", "price": 95.0}, {"code": "12001", "desc": "Simple Repair of Superficial Wounds (Stitches)", "price": 487.0}, {"code": "12001", "desc": "Simple Repair of Superficial Wounds (Stitches)", "price": 574.0}, {"code": "99285", "desc": "ER Visit, Level 5 (Complex/Heart Attack)", "price": 1682.0}, {"code": "74177", "desc": "CT Scan Abdomen and Pelvis with Dye", "price": 2509.0}, {"code": "99285", "desc": "ER Visit, Level 5 (Complex/Heart Attack)", "price": 3000.0}, {"code": "59400", "desc": "Obstetrical Care (Labor and Delivery)", "price": 8974.0}, {"code": "59400", "desc": "Obstetrical Care (Labor and Delivery)", "price": 9883.0}, {"code": "59400", "desc": "Obstetrical Care (Labor and Delivery)", "price": 10071.0}, {"code": "27130", "desc": "Hip Replacement", "price": 30288.0}]}